{
    "particleeffect": {
        "activetime": {
            "value": "1.0"
        },
        "dampingforce": {
            "value": "1.0"
        },
        "direction": {
            "max": "0.0 1.0 0.0",
            "min": "0.0 1.0 0.0",
            "value": "Direction"
        },
        "emissionrate": {
            "max": "50.0",
            "min": "50.0"
        },
        "emitterScaleCurve": [

        ],
        "emitterscale": [

        ],
        "emittersize": {
            "value": "7.0 0.0 7.0"
        },
        "emittertype": {
            "value": "Cylinder"
        },
        "numparticles": {
            "value": "1000"
        },
        "relative": {
            "enable": "true"
        },
        "texture": {
            "ani": {
                "fps": "3",
                "name": "textures/sfxs/cs_carnival_weapon_fire",
                "shuffle": false
            },
            "name": "textures/sfxs/cs_carnival_weapon_fire"
        },
        "thickness": {
            "value": "1.0"
        },
        "velocity": {
            "max": "8.0",
            "min": "8.0"
        }
    }
}